CHANGELOG.md
tempo/__init__.py
tempo/cli.py
tempo/ratelimiter.py
tempo/run.py
tempo_async-0.1.1.dist-info/WHEEL
tempo_async-0.1.1.dist-info/METADATA
tempo_async-0.1.1.dist-info/RECORD
