Metadata-Version: 2.1
Name: tempo-async
Version: 0.1.1
Summary: An HTTP package for metering and managing async requests.
Home-page: https://github.com/NicholasBallard/tempo
License: Apache-2.0
Keywords: async,asynchronous,requests,HTTP,meter
Author: Nicholas Ballard
Author-email: nicholasericballard@gmail.com
Maintainer: Nicholas Ballard
Maintainer-email: nicholasericballard@gmail.com
Requires-Python: >=3.10,<4.0
Classifier: Development Status :: 4 - Beta
Classifier: Framework :: AsyncIO
Classifier: License :: OSI Approved :: Apache Software License
Classifier: Programming Language :: Python :: 3
Classifier: Programming Language :: Python :: 3.10
Classifier: Topic :: Internet
Classifier: Topic :: Internet :: WWW/HTTP :: Site Management :: Link Checking
Classifier: Topic :: Utilities
Requires-Dist: click (>=8.0.3,<9.0.0)
Requires-Dist: httpx (>=0.21.1,<0.22.0)
Requires-Dist: nest-asyncio (>=1.5.4,<2.0.0)
Requires-Dist: pydantic (>=1.9.0,<2.0.0)
Project-URL: Repository, https://github.com/NicholasBallard/tempo
